deepsynthbody/__init__.py
deepsynthbody/cardiovascular/__init__.py
deepsynthbody/cardiovascular/ecg/__init__.py
deepsynthbody/cardiovascular/ecg/functions.py
deepsynthbody/digestive/__init__.py
deepsynthbody/digestive/gitract/__init__.py
deepsynthbody/digestive/gitract/functions.py
deepsynthbody-1.0.2.dist-info/LICENSE
deepsynthbody-1.0.2.dist-info/METADATA
deepsynthbody-1.0.2.dist-info/WHEEL
deepsynthbody-1.0.2.dist-info/top_level.txt
deepsynthbody-1.0.2.dist-info/RECORD
