Metadata-Version: 2.1
Name: deepsynthbody
Version: 1.0.2
Summary: Unlimited deep synthetic medical data generators
Home-page: https://github.com/vlbthambawita/deepsynthbody
Author: Vajira Thambawita
Author-email: vlbthambawita@gmail.com
License: UNKNOWN
Platform: UNKNOWN
Classifier: Programming Language :: Python :: 3
Classifier: License :: OSI Approved :: MIT License
Classifier: Operating System :: OS Independent
Requires-Python: >=3.6
Requires-Dist: deepsynth-gitract
Requires-Dist: deepfake-ecg
